newpkg/__init__.py
newpkg/code.py
new_pkgsetup-0.1.9.dist-info/LICENSE
new_pkgsetup-0.1.9.dist-info/METADATA
new_pkgsetup-0.1.9.dist-info/WHEEL
new_pkgsetup-0.1.9.dist-info/top_level.txt
new_pkgsetup-0.1.9.dist-info/RECORD
