Metadata-Version: 2.1
Name: new-pkgsetup
Version: 0.1.9
Summary: package build using setuptools
Home-page: https://github.com/mkner/new-pkgsetup/
License: MIT
Keywords: python,packages
Platform: UNKNOWN
Classifier: Programming Language :: Python :: 3
Classifier: License :: OSI Approved :: MIT License
Classifier: Operating System :: OS Independent
License-File: LICENSE
